[
  {
    "units": [
      "Swain",
      "Ambessa",
      "Mordekaiser",
      "Rumble",
      "Ekko",
      "Illaoi",
      "Smeech"
    ],
    "activated_traits": [
      {
        "name": "Scrap",
        "count": 2,
        "breakpoint_hit": 2
      },
      {
        "name": "Emissary",
        "count": 1,
        "breakpoint_hit": 1
      },
      {
        "name": "Sentinel",
        "count": 2,
        "breakpoint_hit": 2
      },
      {
        "name": "Ambusher",
        "count": 2,
        "breakpoint_hit": 2
      },
      {
        "name": "Conqueror",
        "count": 4,
        "breakpoint_hit": 4
      },
      {
        "name": "Junker King",
        "count": 1,
        "breakpoint_hit": 1
      }
    ],
    "total_traits_activated": 6
  },
  {
    "units": [
      "Swain",
      "Ambessa",
      "Draven",
      "Rumble",
      "Ekko",
      "Illaoi",
      "Smeech",
      "Sevika"
    ],
    "activated_traits": [
      {
        "name": "Scrap",
        "count": 2,
        "breakpoint_hit": 2
      },
      {
        "name": "Emissary",
        "count": 1,
        "breakpoint_hit": 1
      },
      {
        "name": "Sentinel",
        "count": 2,
        "breakpoint_hit": 2
      },
      {
        "name": "Ambusher",
        "count": 2,
        "breakpoint_hit": 2
      },
      {
        "name": "Conqueror",
        "count": 4,
        "breakpoint_hit": 4
      },
      {
        "name": "High Roller",
        "count": 1,
        "breakpoint_hit": 1
      },
      {
        "name": "Pit Fighter",
        "count": 2,
        "breakpoint_hit": 2
      },
      {
        "name": "Junker King",
        "count": 1,
        "breakpoint_hit": 1
      }
    ],
    "total_traits_activated": 8
  },
  {
    "units": [
      "Swain",
      "Ambessa",
      "Mordekaiser",
      "Rumble",
      "Ekko",
      "Illaoi",
      "Smeech",
      "Sevika",
      "Silco"
    ],
    "activated_traits": [
      {
        "name": "Scrap",
        "count": 2,
        "breakpoint_hit": 2
      },
      {
        "name": "Emissary",
        "count": 1,
        "breakpoint_hit": 1
      },
      {
        "name": "Sentinel",
        "count": 2,
        "breakpoint_hit": 2
      },
      {
        "name": "Ambusher",
        "count": 2,
        "breakpoint_hit": 2
      },
      {
        "name": "Conqueror",
        "count": 4,
        "breakpoint_hit": 4
      },
      {
        "name": "High Roller",
        "count": 1,
        "breakpoint_hit": 1
      },
      {
        "name": "Chem-Baron",
        "count": 3,
        "breakpoint_hit": 3
      },
      {
        "name": "Dominator",
        "count": 2,
        "breakpoint_hit": 2
      },
      {
        "name": "Junker King",
        "count": 1,
        "breakpoint_hit": 1
      }
    ],
    "total_traits_activated": 9
  },
  {
    "units": [
      "Swain",
      "Ambessa",
      "Mordekaiser",
      "Rumble",
      "Ekko",
      "Illaoi",
      "Smeech",
      "Sevika",
      "Silco",
      "Gangplank"
    ],
    "activated_traits": [
      {
        "name": "Scrap",
        "count": 3,
        "breakpoint_hit": 2
      },
      {
        "name": "Form Swapper",
        "count": 2,
        "breakpoint_hit": 2
      },
      {
        "name": "Emissary",
        "count": 1,
        "breakpoint_hit": 1
      },
      {
        "name": "Sentinel",
        "count": 2,
        "breakpoint_hit": 2
      },
      {
        "name": "Ambusher",
        "count": 2,
        "breakpoint_hit": 2
      },
      {
        "name": "Conqueror",
        "count": 4,
        "breakpoint_hit": 4
      },
      {
        "name": "High Roller",
        "count": 1,
        "breakpoint_hit": 1
      },
      {
        "name": "Chem-Baron",
        "count": 3,
        "breakpoint_hit": 3
      },
      {
        "name": "Dominator",
        "count": 2,
        "breakpoint_hit": 2
      },
      {
        "name": "Pit Fighter",
        "count": 2,
        "breakpoint_hit": 2
      },
      {
        "name": "Junker King",
        "count": 1,
        "breakpoint_hit": 1
      }
    ],
    "total_traits_activated": 11
  }
]